[
    {
        "id": 1,
        "province_id": 11,
        "name": "Santa Rosa"
    },
    {
        "id": 2,
        "province_id": 11,
        "name": "General Pico"
    },
    {
        "id": 3,
        "province_id": 11,
        "name": "Toay"
    },
    {
        "id": 4,
        "province_id": 11,
        "name": "Realicó"
    },
    {
        "id": 5,
        "province_id": 11,
        "name": "Macachín"
    },
    {
        "id": 6,
        "province_id": 11,
        "name": "Quemú Quemú"
    },
    {
        "id": 7,
        "province_id": 11,
        "name": "General Acha"
    },
    {
        "id": 8,
        "province_id": 11,
        "name": "Eduardo Castex"
    },
    {
        "id": 9,
        "province_id": 11,
        "name": "General Campos"
    },
    {
        "id": 10,
        "province_id": 11,
        "name": "Trenel"
    }
]

